senderscore/__init__.py
senderscore/senderscore.py
senderscore-0.1.6.dist-info/LICENSE
senderscore-0.1.6.dist-info/METADATA
senderscore-0.1.6.dist-info/WHEEL
senderscore-0.1.6.dist-info/entry_points.txt
senderscore-0.1.6.dist-info/top_level.txt
senderscore-0.1.6.dist-info/RECORD
