Metadata-Version: 2.1
Name: senderscore
Version: 0.1.6
Summary: Senderscore command line lookup tool
Home-page: https://github.com/undersfx/senderscore-lookup
Author: Thiago "Undersfx" Rodrigues
License: MIT
Keywords: sender score lookup cli undersfx
Platform: UNKNOWN
Classifier: Programming Language :: Python :: 3
Classifier: License :: OSI Approved :: MIT License
Classifier: Operating System :: OS Independent
License-File: LICENSE
